graphs_jpoyner1/__init__.py
graphs_jpoyner1/heapq.py
graphs_jpoyner1/sp.py
graphs_jpoyner1-0.0.1.dist-info/METADATA
graphs_jpoyner1-0.0.1.dist-info/WHEEL
graphs_jpoyner1-0.0.1.dist-info/RECORD
